star_rail_parser/__init__.py
star_rail_parser/ability.py
star_rail_parser/character.py
star_rail_parser/lightcone.py
star_rail_parser/relic.py
star_rail_parser/relic_set.py
star_rail_parser/skilltree.py
star_rail_parser/stat.py
star_rail_parser/trailblazer.py
star_rail_parser-0.1.0.dist-info/LICENSE
star_rail_parser-0.1.0.dist-info/METADATA
star_rail_parser-0.1.0.dist-info/WHEEL
star_rail_parser-0.1.0.dist-info/top_level.txt
star_rail_parser-0.1.0.dist-info/RECORD
