Metadata-Version: 2.1
Name: star-rail-parser
Version: 0.1.0
Summary: A simple Python package for using data from the official mihomo API
Author-email: Vighnesh Mandavkar <vighnesh_mandavkar@outlook.com>
License: MIT License
Project-URL: Homepage, https://github.com/infernodragon456/star-rail-parser
Classifier: License :: OSI Approved :: MIT License
Classifier: Programming Language :: Python
Classifier: Programming Language :: Python :: 3
Classifier: Programming Language :: Python :: 3.10
Requires-Python: >=3.9
License-File: LICENSE
Requires-Dist: requests >=2.32.3
